atlasq/__init__.py
atlasq/queryset/__init__.py
atlasq/queryset/exceptions.py
atlasq/queryset/index.py
atlasq/queryset/manager.py
atlasq/queryset/node.py
atlasq/queryset/queryset.py
atlasq/queryset/transform.py
atlasq/queryset/visitor.py
atlasq_tschaume-0.11.1.dev2.dist-info/LICENSE.txt
atlasq_tschaume-0.11.1.dev2.dist-info/METADATA
atlasq_tschaume-0.11.1.dev2.dist-info/WHEEL
atlasq_tschaume-0.11.1.dev2.dist-info/top_level.txt
atlasq_tschaume-0.11.1.dev2.dist-info/RECORD
