Metadata-Version: 2.1
Name: atlasq-tschaume
Version: 0.11.1.dev2
Summary: Query proxy that allows the usage of AtlasSearch with mongoengine specific syntax
Maintainer-email: Simone Berni <s.berni@certego.net>, Patrick Huck <phuck@lbl.gov>
License: MIT License
Project-URL: homepage, https://github.com/tschaume/atlasq
Project-URL: repository, https://github.com/tschaume/atlasq
Project-URL: documentation, https://github.com/tschaume/atlasq/README.md
Project-URL: source, https://github.com/tschaume/atlasq
Project-URL: tracker, https://github.com/tschaume/atlasq/issues
Keywords: certego,atlas,mongoengine,python,search,textsearch,atlassearch
Classifier: Development Status :: 3 - Alpha
Classifier: Intended Audience :: Developers
Classifier: License :: OSI Approved :: BSD License
Classifier: Programming Language :: Python :: 3.6
Classifier: Programming Language :: Python :: 3.7
Classifier: Programming Language :: Python :: 3.8
Classifier: Programming Language :: Python :: 3.9
Classifier: Programming Language :: Python :: 3.10
Classifier: Topic :: Software Development :: Libraries :: Python Modules
Requires-Python: >=3.6
License-File: LICENSE.txt
Requires-Dist: mongoengine (>=0.22.0)
Requires-Dist: requests (>=2.18.0)
Provides-Extra: test
Requires-Dist: black (==22.3.0) ; extra == 'test'
Requires-Dist: isort (==5.10.1) ; extra == 'test'
Requires-Dist: pylint (==2.13.9) ; extra == 'test'
Requires-Dist: flake8 (==4.0.1) ; extra == 'test'
Requires-Dist: pre-commit (==2.19.0) ; extra == 'test'
Requires-Dist: tox (==3.25.0) ; extra == 'test'
Requires-Dist: tox-gh-actions (==2.9.1) ; extra == 'test'
Requires-Dist: codecov (==2.1.12) ; extra == 'test'
Requires-Dist: coverage (==6.4) ; extra == 'test'
Requires-Dist: mongomock (==4.0.0) ; extra == 'test'
